{"nodes": [{"id": "d_git_cash_ledger_github_to_app123_src_mobile_components_syncstatusdisplay_tsx", "label": "SyncStatusDisplay.tsx", "file_type": "code", "source_file": "D:\\git\\CASH LEDGER\\github-to-app123\\src\\mobile\\components\\SyncStatusDisplay.tsx", "source_location": "L1"}, {"id": "components_syncstatusdisplay_loadstats", "label": "loadStats()", "file_type": "code", "source_file": "D:\\git\\CASH LEDGER\\github-to-app123\\src\\mobile\\components\\SyncStatusDisplay.tsx", "source_location": "L48"}, {"id": "components_syncstatusdisplay_handlemanualsync", "label": "handleManualSync()", "file_type": "code", "source_file": "D:\\git\\CASH LEDGER\\github-to-app123\\src\\mobile\\components\\SyncStatusDisplay.tsx", "source_location": "L61"}], "edges": [{"source": "d_git_cash_ledger_github_to_app123_src_mobile_components_syncstatusdisplay_tsx", "target": "react", "relation": "imports_from", "context": "import", "confidence": "EXTRACTED", "source_file": "D:\\git\\CASH LEDGER\\github-to-app123\\src\\mobile\\components\\SyncStatusDisplay.tsx", "source_location": "L1", "weight": 1.0}, {"source": "d_git_cash_ledger_github_to_app123_src_mobile_components_syncstatusdisplay_tsx", "target": "d_git_cash_ledger_github_to_app123_src_components_ui_card", "relation": "imports_from", "context": "import", "confidence": "EXTRACTED", "source_file": "D:\\git\\CASH LEDGER\\github-to-app123\\src\\mobile\\components\\SyncStatusDisplay.tsx", "source_location": "L2", "weight": 1.0}, {"source": "d_git_cash_ledger_github_to_app123_src_mobile_components_syncstatusdisplay_tsx", "target": "ui_card_card", "relation": "imports", "context": "import", "confidence": "EXTRACTED", "source_file": "D:\\git\\CASH LEDGER\\github-to-app123\\src\\mobile\\components\\SyncStatusDisplay.tsx", "source_location": "L2", "weight": 1.0}, {"source": "d_git_cash_ledger_github_to_app123_src_mobile_components_syncstatusdisplay_tsx", "target": "ui_card_cardcontent", "relation": "imports", "context": "import", "confidence": "EXTRACTED", "source_file": "D:\\git\\CASH LEDGER\\github-to-app123\\src\\mobile\\components\\SyncStatusDisplay.tsx", "source_location": "L2", "weight": 1.0}, {"source": "d_git_cash_ledger_github_to_app123_src_mobile_components_syncstatusdisplay_tsx", "target": "d_git_cash_ledger_github_to_app123_src_components_ui_button", "relation": "imports_from", "context": "import", "confidence": "EXTRACTED", "source_file": "D:\\git\\CASH LEDGER\\github-to-app123\\src\\mobile\\components\\SyncStatusDisplay.tsx", "source_location": "L3", "weight": 1.0}, {"source": "d_git_cash_ledger_github_to_app123_src_mobile_components_syncstatusdisplay_tsx", "target": "ui_button_button", "relation": "imports", "context": "import", "confidence": "EXTRACTED", "source_file": "D:\\git\\CASH LEDGER\\github-to-app123\\src\\mobile\\components\\SyncStatusDisplay.tsx", "source_location": "L3", "weight": 1.0}, {"source": "d_git_cash_ledger_github_to_app123_src_mobile_components_syncstatusdisplay_tsx", "target": "d_git_cash_ledger_github_to_app123_src_components_ui_progress", "relation": "imports_from", "context": "import", "confidence": "EXTRACTED", "source_file": "D:\\git\\CASH LEDGER\\github-to-app123\\src\\mobile\\components\\SyncStatusDisplay.tsx", "source_location": "L4", "weight": 1.0}, {"source": "d_git_cash_ledger_github_to_app123_src_mobile_components_syncstatusdisplay_tsx", "target": "ui_progress_progress", "relation": "imports", "context": "import", "confidence": "EXTRACTED", "source_file": "D:\\git\\CASH LEDGER\\github-to-app123\\src\\mobile\\components\\SyncStatusDisplay.tsx", "source_location": "L4", "weight": 1.0}, {"source": "d_git_cash_ledger_github_to_app123_src_mobile_components_syncstatusdisplay_tsx", "target": "lucide_react", "relation": "imports_from", "context": "import", "confidence": "EXTRACTED", "source_file": "D:\\git\\CASH LEDGER\\github-to-app123\\src\\mobile\\components\\SyncStatusDisplay.tsx", "source_location": "L5", "weight": 1.0}, {"source": "d_git_cash_ledger_github_to_app123_src_mobile_components_syncstatusdisplay_tsx", "target": "d_git_cash_ledger_github_to_app123_src_mobile_services_sync_service", "relation": "imports_from", "context": "import", "confidence": "EXTRACTED", "source_file": "D:\\git\\CASH LEDGER\\github-to-app123\\src\\mobile\\components\\SyncStatusDisplay.tsx", "source_location": "L6", "weight": 1.0}, {"source": "d_git_cash_ledger_github_to_app123_src_mobile_components_syncstatusdisplay_tsx", "target": "services_sync_syncservice", "relation": "imports", "context": "import", "confidence": "EXTRACTED", "source_file": "D:\\git\\CASH LEDGER\\github-to-app123\\src\\mobile\\components\\SyncStatusDisplay.tsx", "source_location": "L6", "weight": 1.0}, {"source": "d_git_cash_ledger_github_to_app123_src_mobile_components_syncstatusdisplay_tsx", "target": "services_sync_syncprogress", "relation": "imports", "context": "import", "confidence": "EXTRACTED", "source_file": "D:\\git\\CASH LEDGER\\github-to-app123\\src\\mobile\\components\\SyncStatusDisplay.tsx", "source_location": "L6", "weight": 1.0}, {"source": "d_git_cash_ledger_github_to_app123_src_mobile_components_syncstatusdisplay_tsx", "target": "d_git_cash_ledger_github_to_app123_src_mobile_services_database_service", "relation": "imports_from", "context": "import", "confidence": "EXTRACTED", "source_file": "D:\\git\\CASH LEDGER\\github-to-app123\\src\\mobile\\components\\SyncStatusDisplay.tsx", "source_location": "L7", "weight": 1.0}, {"source": "d_git_cash_ledger_github_to_app123_src_mobile_components_syncstatusdisplay_tsx", "target": "services_database_databaseservice", "relation": "imports", "context": "import", "confidence": "EXTRACTED", "source_file": "D:\\git\\CASH LEDGER\\github-to-app123\\src\\mobile\\components\\SyncStatusDisplay.tsx", "source_location": "L7", "weight": 1.0}, {"source": "d_git_cash_ledger_github_to_app123_src_mobile_components_syncstatusdisplay_tsx", "target": "d_git_cash_ledger_github_to_app123_src_mobile_services_network_service", "relation": "imports_from", "context": "import", "confidence": "EXTRACTED", "source_file": "D:\\git\\CASH LEDGER\\github-to-app123\\src\\mobile\\components\\SyncStatusDisplay.tsx", "source_location": "L8", "weight": 1.0}, {"source": "d_git_cash_ledger_github_to_app123_src_mobile_components_syncstatusdisplay_tsx", "target": "services_network_networkservice", "relation": "imports", "context": "import", "confidence": "EXTRACTED", "source_file": "D:\\git\\CASH LEDGER\\github-to-app123\\src\\mobile\\components\\SyncStatusDisplay.tsx", "source_location": "L8", "weight": 1.0}, {"source": "d_git_cash_ledger_github_to_app123_src_mobile_components_syncstatusdisplay_tsx", "target": "d_git_cash_ledger_github_to_app123_src_mobile_providers_mobileserviceprovider", "relation": "imports_from", "context": "import", "confidence": "EXTRACTED", "source_file": "D:\\git\\CASH LEDGER\\github-to-app123\\src\\mobile\\components\\SyncStatusDisplay.tsx", "source_location": "L9", "weight": 1.0}, {"source": "d_git_cash_ledger_github_to_app123_src_mobile_components_syncstatusdisplay_tsx", "target": "providers_mobileserviceprovider_usemobileservices", "relation": "imports", "context": "import", "confidence": "EXTRACTED", "source_file": "D:\\git\\CASH LEDGER\\github-to-app123\\src\\mobile\\components\\SyncStatusDisplay.tsx", "source_location": "L9", "weight": 1.0}, {"source": "d_git_cash_ledger_github_to_app123_src_mobile_components_syncstatusdisplay_tsx", "target": "components_syncstatusdisplay_loadstats", "relation": "contains", "confidence": "EXTRACTED", "source_file": "D:\\git\\CASH LEDGER\\github-to-app123\\src\\mobile\\components\\SyncStatusDisplay.tsx", "source_location": "L48", "weight": 1.0}, {"source": "d_git_cash_ledger_github_to_app123_src_mobile_components_syncstatusdisplay_tsx", "target": "components_syncstatusdisplay_handlemanualsync", "relation": "contains", "confidence": "EXTRACTED", "source_file": "D:\\git\\CASH LEDGER\\github-to-app123\\src\\mobile\\components\\SyncStatusDisplay.tsx", "source_location": "L61", "weight": 1.0}, {"source": "components_syncstatusdisplay_handlemanualsync", "target": "components_syncstatusdisplay_loadstats", "relation": "calls", "context": "call", "confidence": "EXTRACTED", "source_file": "D:\\git\\CASH LEDGER\\github-to-app123\\src\\mobile\\components\\SyncStatusDisplay.tsx", "source_location": "L72", "weight": 1.0}], "raw_calls": [{"caller_nid": "components_syncstatusdisplay_loadstats", "callee": "all", "is_member_call": true, "source_file": "D:\\git\\CASH LEDGER\\github-to-app123\\src\\mobile\\components\\SyncStatusDisplay.tsx", "source_location": "L50"}, {"caller_nid": "components_syncstatusdisplay_loadstats", "callee": "getSyncStats", "is_member_call": true, "source_file": "D:\\git\\CASH LEDGER\\github-to-app123\\src\\mobile\\components\\SyncStatusDisplay.tsx", "source_location": "L51"}, {"caller_nid": "components_syncstatusdisplay_loadstats", "callee": "getTableCounts", "is_member_call": true, "source_file": "D:\\git\\CASH LEDGER\\github-to-app123\\src\\mobile\\components\\SyncStatusDisplay.tsx", "source_location": "L52"}, {"caller_nid": "components_syncstatusdisplay_loadstats", "callee": "setStats", "is_member_call": false, "source_file": "D:\\git\\CASH LEDGER\\github-to-app123\\src\\mobile\\components\\SyncStatusDisplay.tsx", "source_location": "L54"}, {"caller_nid": "components_syncstatusdisplay_loadstats", "callee": "setTableCounts", "is_member_call": false, "source_file": "D:\\git\\CASH LEDGER\\github-to-app123\\src\\mobile\\components\\SyncStatusDisplay.tsx", "source_location": "L55"}, {"caller_nid": "components_syncstatusdisplay_loadstats", "callee": "error", "is_member_call": true, "source_file": "D:\\git\\CASH LEDGER\\github-to-app123\\src\\mobile\\components\\SyncStatusDisplay.tsx", "source_location": "L57"}, {"caller_nid": "components_syncstatusdisplay_handlemanualsync", "callee": "startSync", "is_member_call": true, "source_file": "D:\\git\\CASH LEDGER\\github-to-app123\\src\\mobile\\components\\SyncStatusDisplay.tsx", "source_location": "L66"}, {"caller_nid": "components_syncstatusdisplay_handlemanualsync", "callee": "downloadLatestData", "is_member_call": true, "source_file": "D:\\git\\CASH LEDGER\\github-to-app123\\src\\mobile\\components\\SyncStatusDisplay.tsx", "source_location": "L68"}, {"caller_nid": "components_syncstatusdisplay_handlemanualsync", "callee": "dispatchEvent", "is_member_call": true, "source_file": "D:\\git\\CASH LEDGER\\github-to-app123\\src\\mobile\\components\\SyncStatusDisplay.tsx", "source_location": "L70"}, {"caller_nid": "components_syncstatusdisplay_handlemanualsync", "callee": "error", "is_member_call": true, "source_file": "D:\\git\\CASH LEDGER\\github-to-app123\\src\\mobile\\components\\SyncStatusDisplay.tsx", "source_location": "L74"}]}